vcf_batcher-0.2.1.dist-info/METADATA
vcf_batcher-0.2.1.dist-info/WHEEL
vcf_batcher/__init__.py
vcf_batcher/__init__.pyi
vcf_batcher/py.typed
vcf_batcher/vcf_batcher.cpython-310-x86_64-linux-gnu.so
vcf_batcher-0.2.1.dist-info/RECORD
